
{
  "header": {
    "reportVersion": 1,
    "event": "Allocation failed - JavaScript heap out of memory",
    "trigger": "FatalError",
    "filename": "report.20200727.222322.10510.0.001.json",
    "dumpEventTime": "2020-07-27T22:23:23Z",
    "dumpEventTimeStamp": "1595899403032",
    "processId": 10510,
    "cwd": "/home/fsegall/Desktop/Omni/GoStack11/health-backend",
    "commandLine": [
      "node",
      "-r",
      "esm",
      "dist/shared/infra/http/server.js"
    ],
    "nodejsVersion": "v13.1.0",
    "glibcVersionRuntime": "2.27",
    "glibcVersionCompiler": "2.17",
    "wordSize": 64,
    "arch": "x64",
    "platform": "linux",
    "componentVersions": {
      "node": "13.1.0",
      "v8": "7.8.279.17-node.19",
      "uv": "1.33.1",
      "zlib": "1.2.11",
      "brotli": "1.0.7",
      "ares": "1.15.0",
      "modules": "79",
      "nghttp2": "1.39.2",
      "napi": "5",
      "llhttp": "1.1.4",
      "openssl": "1.1.1d",
      "cldr": "35.1",
      "icu": "64.2",
      "tz": "2019a",
      "unicode": "12.1"
    },
    "release": {
      "name": "node",
      "headersUrl": "https://nodejs.org/download/release/v13.1.0/node-v13.1.0-headers.tar.gz",
      "sourceUrl": "https://nodejs.org/download/release/v13.1.0/node-v13.1.0.tar.gz"
    },
    "osName": "Linux",
    "osRelease": "4.15.0-58-generic",
    "osVersion": "#64-Ubuntu SMP Tue Aug 6 11:12:41 UTC 2019",
    "osMachine": "x86_64",
    "cpus": [
      {
        "model": "Intel(R) Core(TM) i7-2640M CPU @ 2.80GHz",
        "speed": 3292,
        "user": 273602800,
        "nice": 161100,
        "sys": 60904100,
        "idle": 1599032600,
        "irq": 0
      },
      {
        "model": "Intel(R) Core(TM) i7-2640M CPU @ 2.80GHz",
        "speed": 3292,
        "user": 268874000,
        "nice": 253200,
        "sys": 61642300,
        "idle": 371501500,
        "irq": 0
      },
      {
        "model": "Intel(R) Core(TM) i7-2640M CPU @ 2.80GHz",
        "speed": 3292,
        "user": 269124700,
        "nice": 143500,
        "sys": 64645300,
        "idle": 370225400,
        "irq": 0
      },
      {
        "model": "Intel(R) Core(TM) i7-2640M CPU @ 2.80GHz",
        "speed": 3292,
        "user": 267060800,
        "nice": 224100,
        "sys": 61685400,
        "idle": 373268400,
        "irq": 0
      }
    ],
    "networkInterfaces": [
      {
        "name": "lo",
        "internal": true,
        "mac": "00:00:00:00:00:00",
        "address": "127.0.0.1",
        "netmask": "255.0.0.0",
        "family": "IPv4"
      },
      {
        "name": "wlp9s0",
        "internal": false,
        "mac": "e0:06:e6:fb:83:af",
        "address": "192.168.0.7",
        "netmask": "255.255.255.0",
        "family": "IPv4"
      },
      {
        "name": "docker0",
        "internal": false,
        "mac": "02:42:2e:61:c7:ca",
        "address": "172.17.0.1",
        "netmask": "255.255.0.0",
        "family": "IPv4"
      },
      {
        "name": "ppp0",
        "internal": false,
        "mac": "00:00:00:00:00:00",
        "address": "192.168.32.98",
        "netmask": "255.255.255.255",
        "family": "IPv4"
      },
      {
        "name": "lo",
        "internal": true,
        "mac": "00:00:00:00:00:00",
        "address": "::1",
        "netmask": "ffff:ffff:ffff:ffff:ffff:ffff:ffff:ffff",
        "family": "IPv6",
        "scopeid": 0
      },
      {
        "name": "wlp9s0",
        "internal": false,
        "mac": "e0:06:e6:fb:83:af",
        "address": "2804:14c:6583:4203:1cf5:1b02:f2c2:78ef",
        "netmask": "ffff:ffff:ffff:ffff::",
        "family": "IPv6",
        "scopeid": 0
      },
      {
        "name": "wlp9s0",
        "internal": false,
        "mac": "e0:06:e6:fb:83:af",
        "address": "2804:14c:6583:4203:60c0:621a:1f3c:b4bb",
        "netmask": "ffff:ffff:ffff:ffff::",
        "family": "IPv6",
        "scopeid": 0
      },
      {
        "name": "wlp9s0",
        "internal": false,
        "mac": "e0:06:e6:fb:83:af",
        "address": "fe80::33fb:9194:f5e7:b07c",
        "netmask": "ffff:ffff:ffff:ffff::",
        "family": "IPv6",
        "scopeid": 3
      },
      {
        "name": "docker0",
        "internal": false,
        "mac": "02:42:2e:61:c7:ca",
        "address": "fe80::42:2eff:fe61:c7ca",
        "netmask": "ffff:ffff:ffff:ffff::",
        "family": "IPv6",
        "scopeid": 7
      },
      {
        "name": "vethdea06a4",
        "internal": false,
        "mac": "3e:ca:50:3e:de:19",
        "address": "fe80::3cca:50ff:fe3e:de19",
        "netmask": "ffff:ffff:ffff:ffff::",
        "family": "IPv6",
        "scopeid": 11
      }
    ],
    "host": "what-r-u-up-2"
  },
  "javascriptStack": {
    "message": "No stack.",
    "stack": [
      "Unavailable."
    ]
  },
  "nativeStack": [
    {
      "pc": "0x0000000000b10715",
      "symbol": "report::TriggerNodeReport(v8::Isolate*, node::Environment*, char const*, char const*, std::string const&, v8::Local<v8::String>) [node]"
    },
    {
      "pc": "0x00000000009ec1cc",
      "symbol": "node::OnFatalError(char const*, char const*) [node]"
    },
    {
      "pc": "0x0000000000b4611e",
      "symbol": "v8::Utils::ReportOOMFailure(v8::internal::Isolate*, char const*, bool) [node]"
    },
    {
      "pc": "0x0000000000b46499",
      "symbol": "v8::internal::V8::FatalProcessOutOfMemory(v8::internal::Isolate*, char const*, bool) [node]"
    },
    {
      "pc": "0x0000000000cf3535",
      "symbol": " [node]"
    },
    {
      "pc": "0x0000000000cf3bc6",
      "symbol": "v8::internal::Heap::RecomputeLimits(v8::internal::GarbageCollector) [node]"
    },
    {
      "pc": "0x0000000000d003fa",
      "symbol": "v8::internal::Heap::PerformGarbageCollection(v8::internal::GarbageCollector, v8::GCCallbackFlags) [node]"
    },
    {
      "pc": "0x0000000000d01305",
      "symbol": "v8::internal::Heap::CollectGarbage(v8::internal::AllocationSpace, v8::internal::GarbageCollectionReason, v8::GCCallbackFlags) [node]"
    },
    {
      "pc": "0x0000000000d03dac",
      "symbol": "v8::internal::Heap::AllocateRawWithRetryOrFail(int, v8::internal::AllocationType, v8::internal::AllocationOrigin, v8::internal::AllocationAlignment) [node]"
    },
    {
      "pc": "0x0000000000cca66b",
      "symbol": "v8::internal::Factory::NewFillerObject(int, bool, v8::internal::AllocationType, v8::internal::AllocationOrigin) [node]"
    },
    {
      "pc": "0x000000000100eb9e",
      "symbol": "v8::internal::Runtime_AllocateInYoungGeneration(int, unsigned long*, v8::internal::Isolate*) [node]"
    },
    {
      "pc": "0x0000000001391439",
      "symbol": " [node]"
    }
  ],
  "javascriptHeap": {
    "totalMemory": 2151739392,
    "totalCommittedMemory": 2150072552,
    "usedMemory": 2143949960,
    "availableMemory": 48144168,
    "memoryLimit": 2197815296,
    "heapSpaces": {
      "read_only_space": {
        "memorySize": 262144,
        "committedMemory": 33088,
        "capacity": 32808,
        "used": 32808,
        "available": 0
      },
      "new_space": {
        "memorySize": 2097152,
        "committedMemory": 1187088,
        "capacity": 1047456,
        "used": 137472,
        "available": 909984
      },
      "old_space": {
        "memorySize": 1873915904,
        "committedMemory": 1873526584,
        "capacity": 1870870584,
        "used": 1870759760,
        "available": 110824
      },
      "code_space": {
        "memorySize": 692224,
        "committedMemory": 580480,
        "capacity": 555904,
        "used": 555904,
        "available": 0
      },
      "map_space": {
        "memorySize": 3936256,
        "committedMemory": 3909600,
        "capacity": 1716400,
        "used": 1716400,
        "available": 0
      },
      "large_object_space": {
        "memorySize": 270786560,
        "committedMemory": 270786560,
        "capacity": 270744832,
        "used": 270744832,
        "available": 0
      },
      "code_large_object_space": {
        "memorySize": 49152,
        "committedMemory": 49152,
        "capacity": 2784,
        "used": 2784,
        "available": 0
      },
      "new_large_object_space": {
        "memorySize": 0,
        "committedMemory": 0,
        "capacity": 1047456,
        "used": 0,
        "available": 1047456
      }
    }
  },
  "resourceUsage": {
    "userCpuSeconds": 465.409,
    "kernelCpuSeconds": 6.92594,
    "cpuConsumptionPercent": 145.334,
    "maxRss": 2980155392,
    "pageFaults": {
      "IORequired": 181,
      "IONotRequired": 930319
    },
    "fsActivity": {
      "reads": 41376,
      "writes": 16
    }
  },
  "uvthreadResourceUsage": {
    "userCpuSeconds": 161.668,
    "kernelCpuSeconds": 2.66049,
    "cpuConsumptionPercent": 50.5626,
    "fsActivity": {
      "reads": 40440,
      "writes": 16
    }
  },
  "libuv": [
  ],
  "environmentVariables": {
    "J2SDKDIR": "/usr/lib/jvm/java-8-oracle",
    "USER": "fsegall",
    "LC_TIME": "pt_BR.UTF-8",
    "TEXTDOMAIN": "im-config",
    "XDG_SEAT": "seat0",
    "XDG_SESSION_TYPE": "x11",
    "SSH_AGENT_PID": "3643",
    "J2REDIR": "/usr/lib/jvm/java-8-oracle/jre",
    "SHLVL": "1",
    "QT4_IM_MODULE": "xim",
    "HOME": "/home/fsegall",
    "DESKTOP_SESSION": "ubuntu",
    "GTK_MODULES": "gail:atk-bridge",
    "GNOME_SHELL_SESSION_MODE": "ubuntu",
    "LC_MONETARY": "pt_BR.UTF-8",
    "LC_CTYPE": "pt_BR.UTF-8",
    "DBUS_SESSION_BUS_ADDRESS": "unix:path=/run/user/1000/bus",
    "LIBVIRT_DEFAULT_URI": "qemu:///system",
    "MANDATORY_PATH": "/usr/share/gconf/ubuntu.mandatory.path",
    "IM_CONFIG_PHASE": "2",
    "LOGNAME": "fsegall",
    "GTK_IM_MODULE": "ibus",
    "DEFAULTS_PATH": "/usr/share/gconf/ubuntu.default.path",
    "USERNAME": "fsegall",
    "XDG_SESSION_ID": "2",
    "WINDOWPATH": "2",
    "PATH": "/home/fsegall/.nvm/versions/node/v13.1.0/bin:/home/fsegall/android-studio/bin:/home/fsegall/Android/Sdk/platform-tools:/home/fsegall/Android/Sdk/tools/bin:/home/fsegall/Android/Sdk/tools:/home/fsegall/Android/Sdk/emulator:/home/fsegall/.yarn/bin:/home/fsegall/.config/yarn/global/node_modules/.bin:/home/fsegall/bin:/usr/local/bin:/home/fsegall/.nvm/versions/node/v13.1.0/bin:/home/fsegall/.zinit/polaris/bin:/home/fsegall/android-studio/bin:/home/fsegall/Android/Sdk/platform-tools:/home/fsegall/Android/Sdk/tools/bin:/home/fsegall/Android/Sdk/tools:/home/fsegall/Android/Sdk/emulator:/home/fsegall/.yarn/bin:/home/fsegall/.config/yarn/global/node_modules/.bin:/home/fsegall/bin:/usr/local/bin:/home/fsegall/.cargo/bin:/home/fsegall/.cargo/bin:/home/fsegall/bin:/usr/local/sbin:/usr/local/bin:/usr/sbin:/usr/bin:/sbin:/bin:/usr/games:/usr/local/games:/home/fsegall/Android/Sdk/tools/bin:/home/linuxbrew/.linuxbrew/bin:/snap/bin:/usr/lib/jvm/java-8-oracle/bin:/usr/lib/jvm/java-8-oracle/db/bin:/usr/lib/jvm/java-8-oracle/jre/bin",
    "DERBY_HOME": "/usr/lib/jvm/java-8-oracle/db",
    "S_COLORS": "auto",
    "LC_ADDRESS": "pt_BR.UTF-8",
    "XDG_RUNTIME_DIR": "/run/user/1000",
    "DISPLAY": ":0",
    "XDG_CURRENT_DESKTOP": "Unity",
    "LC_TELEPHONE": "pt_BR.UTF-8",
    "XDG_SESSION_DESKTOP": "ubuntu",
    "XMODIFIERS": "@im=ibus",
    "XAUTHORITY": "/run/user/1000/gdm/Xauthority",
    "SSH_AUTH_SOCK": "/run/user/1000/keyring/ssh",
    "LC_NAME": "pt_BR.UTF-8",
    "SHELL": "/usr/bin/zsh",
    "QT_ACCESSIBILITY": "1",
    "GDMSESSION": "ubuntu",
    "LC_MEASUREMENT": "pt_BR.UTF-8",
    "TEXTDOMAINDIR": "/usr/share/locale/",
    "GPG_AGENT_INFO": "/run/user/1000/gnupg/S.gpg-agent:0:1",
    "LC_IDENTIFICATION": "pt_BR.UTF-8",
    "XDG_VTNR": "2",
    "QT_IM_MODULE": "ibus",
    "JAVA_HOME": "/usr/lib/jvm/java-8-openjdk-amd64",
    "PWD": "/home/fsegall/Desktop/Omni/GoStack11/health-backend",
    "CLUTTER_IM_MODULE": "xim",
    "XDG_DATA_DIRS": "/usr/share/ubuntu:/usr/local/share/:/usr/share/:/var/lib/snapd/desktop",
    "XDG_CONFIG_DIRS": "/etc/xdg/xdg-ubuntu:/etc/xdg",
    "LC_NUMERIC": "pt_BR.UTF-8",
    "LC_PAPER": "pt_BR.UTF-8",
    "GNOME_DESKTOP_SESSION_ID": "this-is-deprecated",
    "XDG_MENU_PREFIX": "gnome-",
    "SESSION_MANAGER": "local/what-r-u-up-2:@/tmp/.ICE-unix/3547,unix/what-r-u-up-2:/tmp/.ICE-unix/3547",
    "GIO_LAUNCHED_DESKTOP_FILE": "/usr/share/applications/code.desktop",
    "GIO_LAUNCHED_DESKTOP_FILE_PID": "20974",
    "GJS_DEBUG_OUTPUT": "stderr",
    "GJS_DEBUG_TOPICS": "JS ERROR;JS LOG",
    "CHROME_DESKTOP": "code-url-handler.desktop",
    "ORIGINAL_XDG_CURRENT_DESKTOP": "ubuntu:GNOME",
    "ANDROID_HOME": "/home/fsegall/Android/Sdk",
    "LESS": "-R",
    "LSCOLORS": "Gxfxcxdxbxegedabagacad",
    "NVM_BIN": "/home/fsegall/.nvm/versions/node/v13.1.0/bin",
    "NVM_CD_FLAGS": "-q",
    "NVM_DIR": "/home/fsegall/.nvm",
    "OLDPWD": "/home/fsegall/Desktop/Omni/GoStack11",
    "PAGER": "less",
    "PMSPEC": "0uUpiPsf",
    "ZPFX": "/home/fsegall/.zinit/polaris",
    "ZSH": "/home/fsegall/.oh-my-zsh",
    "ZSH_CACHE_DIR": "/home/fsegall/.oh-my-zsh/cache",
    "_": "/home/fsegall/.nvm/versions/node/v13.1.0/bin/node",
    "TERM_PROGRAM": "vscode",
    "TERM_PROGRAM_VERSION": "1.47.1",
    "COLORTERM": "truecolor",
    "VSCODE_GIT_IPC_HANDLE": "/run/user/1000/vscode-git-581be6f3ad.sock",
    "GIT_ASKPASS": "/usr/share/code/resources/app/extensions/git/dist/askpass.sh",
    "VSCODE_GIT_ASKPASS_NODE": "/usr/share/code/code",
    "VSCODE_GIT_ASKPASS_MAIN": "/usr/share/code/resources/app/extensions/git/dist/askpass-main.js",
    "TERM": "xterm-256color",
    "LS_COLORS": "rs=0:di=01;34:ln=01;36:mh=00:pi=40;33:so=01;35:do=01;35:bd=40;33;01:cd=40;33;01:or=40;31;01:mi=00:su=37;41:sg=30;43:ca=30;41:tw=30;42:ow=34;42:st=37;44:ex=01;32:*.tar=01;31:*.tgz=01;31:*.arc=01;31:*.arj=01;31:*.taz=01;31:*.lha=01;31:*.lz4=01;31:*.lzh=01;31:*.lzma=01;31:*.tlz=01;31:*.txz=01;31:*.tzo=01;31:*.t7z=01;31:*.zip=01;31:*.z=01;31:*.Z=01;31:*.dz=01;31:*.gz=01;31:*.lrz=01;31:*.lz=01;31:*.lzo=01;31:*.xz=01;31:*.zst=01;31:*.tzst=01;31:*.bz2=01;31:*.bz=01;31:*.tbz=01;31:*.tbz2=01;31:*.tz=01;31:*.deb=01;31:*.rpm=01;31:*.jar=01;31:*.war=01;31:*.ear=01;31:*.sar=01;31:*.rar=01;31:*.alz=01;31:*.ace=01;31:*.zoo=01;31:*.cpio=01;31:*.7z=01;31:*.rz=01;31:*.cab=01;31:*.wim=01;31:*.swm=01;31:*.dwm=01;31:*.esd=01;31:*.jpg=01;35:*.jpeg=01;35:*.mjpg=01;35:*.mjpeg=01;35:*.gif=01;35:*.bmp=01;35:*.pbm=01;35:*.pgm=01;35:*.ppm=01;35:*.tga=01;35:*.xbm=01;35:*.xpm=01;35:*.tif=01;35:*.tiff=01;35:*.png=01;35:*.svg=01;35:*.svgz=01;35:*.mng=01;35:*.pcx=01;35:*.mov=01;35:*.mpg=01;35:*.mpeg=01;35:*.m2v=01;35:*.mkv=01;35:*.webm=01;35:*.ogm=01;35:*.mp4=01;35:*.m4v=01;35:*.mp4v=01;35:*.vob=01;35:*.qt=01;35:*.nuv=01;35:*.wmv=01;35:*.asf=01;35:*.rm=01;35:*.rmvb=01;35:*.flc=01;35:*.avi=01;35:*.fli=01;35:*.flv=01;35:*.gl=01;35:*.dl=01;35:*.xcf=01;35:*.xwd=01;35:*.yuv=01;35:*.cgm=01;35:*.emf=01;35:*.ogv=01;35:*.ogx=01;35:*.aac=00;36:*.au=00;36:*.flac=00;36:*.m4a=00;36:*.mid=00;36:*.midi=00;36:*.mka=00;36:*.mp3=00;36:*.mpc=00;36:*.ogg=00;36:*.ra=00;36:*.wav=00;36:*.oga=00;36:*.opus=00;36:*.spx=00;36:*.xspf=00;36:",
    "LANG": "en_US.UTF-8"
  },
  "userLimits": {
    "core_file_size_blocks": {
      "soft": 0,
      "hard": "unlimited"
    },
    "data_seg_size_kbytes": {
      "soft": "unlimited",
      "hard": "unlimited"
    },
    "file_size_blocks": {
      "soft": "unlimited",
      "hard": "unlimited"
    },
    "max_locked_memory_bytes": {
      "soft": 16777216,
      "hard": 16777216
    },
    "max_memory_size_kbytes": {
      "soft": "unlimited",
      "hard": "unlimited"
    },
    "open_files": {
      "soft": 1048576,
      "hard": 1048576
    },
    "stack_size_bytes": {
      "soft": 8388608,
      "hard": "unlimited"
    },
    "cpu_time_seconds": {
      "soft": "unlimited",
      "hard": "unlimited"
    },
    "max_user_processes": {
      "soft": 31275,
      "hard": 31275
    },
    "virtual_memory_kbytes": {
      "soft": "unlimited",
      "hard": "unlimited"
    }
  },
  "sharedObjects": [
    "linux-vdso.so.1",
    "/lib/x86_64-linux-gnu/libdl.so.2",
    "/usr/lib/x86_64-linux-gnu/libstdc++.so.6",
    "/lib/x86_64-linux-gnu/libm.so.6",
    "/lib/x86_64-linux-gnu/libgcc_s.so.1",
    "/lib/x86_64-linux-gnu/libpthread.so.0",
    "/lib/x86_64-linux-gnu/libc.so.6",
    "/lib64/ld-linux-x86-64.so.2",
    "/lib/x86_64-linux-gnu/libnss_files.so.2",
    "/lib/x86_64-linux-gnu/libnss_mdns4_minimal.so.2",
    "/lib/x86_64-linux-gnu/libnss_dns.so.2",
    "/lib/x86_64-linux-gnu/libresolv.so.2"
  ]
}